{
  "title": "ウィキニュース、終わり",
  "summary": "ウィキニュースというニュースサイトが閉鎖しました。21年間、多くのニュースを伝えました。残念です。",
  "estimatedMinutes": 3,
  "paragraphs": [
    {
      "text": "ウィキニュースは、21年間続いたニュースサイトです。しかし、このニュースサイトはもうありません。2026年3月30日に、閉鎖することが決まりました。",
      "translationZh": "Wikinews 是一个持续了21年的新闻网站。但是，这个新闻网站已经不存在了。在2026年3月30日，决定关闭。",
      "translationEn": "Wikinews is a news website that continued for 21 years. However, this news website no longer exists. It was decided to close on March 30, 2026.",
      "id": "93c34125-82e7-420a-9ba9-a4f9d52080f5",
      "audioStartMs": null,
      "audioEndMs": null
    },
    {
      "text": "ウィキニュースは、みんなで記事を書くサイトでした。だから、いろいろなニュースがありました。世界中の出来事や、日本の出来事も書かれていました。",
      "translationZh": "Wikinews 是大家一起写文章的网站。因此，有很多各种各样的 news。关于世界各地发生的事件，以及日本发生的事件，都有写。",
      "translationEn": "Wikinews was a site where everyone wrote articles together. Therefore, there were various kinds of news. Events from all over the world and events in Japan were also written.",
      "id": "f4452832-402f-4837-9e30-6fd2d5af2497",
      "audioStartMs": null,
      "audioEndMs": null
    },
    {
      "text": "このサイトは2004年に始まりました。たくさんの人が使って、たくさんの記事を書きました。しかし、最近はあまり更新されなくなりました。それで、閉鎖することになったのです。",
      "translationZh": "这个网站在2004年开始。很多人使用，写了很多文章。但是，最近更新得不多了。因此，就决定关闭了。",
      "translationEn": "This site started in 2004. Many people used it and wrote many articles. However, recently it has not been updated much. Therefore, it was decided to close.",
      "id": "1b0f66e3-34f9-4aff-a82f-938e1adeab58",
      "audioStartMs": null,
      "audioEndMs": null
    },
    {
      "text": "21年間、お疲れ様でした。ウィキニュースは、私たちの記憶に残るでしょう。残念な気持ちですが、新しいニュースサイトの誕生を期待します。",
      "translationZh": "21年来，辛苦了。Wikinews 将留在我们的记忆中。虽然感到遗憾，但我们期待新新闻网站的诞生。",
      "translationEn": "Thank you for your hard work over the 21 years. Wikinews will remain in our memories. Although we feel regret, we look forward to the birth of new news sites.",
      "id": "fa1790da-3b7d-4dd8-b0da-30383265a8e1",
      "audioStartMs": null,
      "audioEndMs": null
    }
  ],
  "vocabulary": [
    {
      "word": "ニュースサイト",
      "reading": "にゅーすさいと",
      "meaningZh": "新闻网站",
      "meaningEn": "news site",
      "level": "n5n4",
      "exampleSentence": "このニュースサイトはとても人気があります。",
      "id": "24b7f8f4-0021-4a8d-975b-8ec8ca65d35b"
    },
    {
      "word": "閉鎖",
      "reading": "へいさ",
      "meaningZh": "关闭",
      "meaningEn": "closure",
      "level": "n5n4",
      "exampleSentence": "お店が閉鎖しました。",
      "id": "1368df7a-9429-44cc-8ccf-1b0da734b0df"
    },
    {
      "word": "決まる",
      "reading": "きまる",
      "meaningZh": "决定",
      "meaningEn": "to be decided",
      "level": "n5n4",
      "exampleSentence": "旅行の場所が決まりました。",
      "id": "c4788ab6-7c06-43ee-bced-942a53e88d4f"
    },
    {
      "word": "記事",
      "reading": "きじ",
      "meaningZh": "文章；报道",
      "meaningEn": "article",
      "level": "n5n4",
      "exampleSentence": "新聞に面白い記事がありました。",
      "id": "66fc5c82-a7fe-49a8-b9c0-36919de7642c"
    },
    {
      "word": "更新",
      "reading": "こうしん",
      "meaningZh": "更新",
      "meaningEn": "update",
      "level": "n5n4",
      "exampleSentence": "アプリを更新しました。",
      "id": "5579a31f-f62a-4837-af5a-1f37d6379c19"
    },
    {
      "word": "残念",
      "reading": "ざんねん",
      "meaningZh": "遗憾；可惜",
      "meaningEn": "regrettable; unfortunate",
      "level": "n5n4",
      "exampleSentence": "試合に負けて残念です。",
      "id": "4500acad-2e37-4c4c-98e2-0aa124eb85a7"
    },
    {
      "word": "記憶",
      "reading": "きおく",
      "meaningZh": "记忆",
      "meaningEn": "memory",
      "level": "n5n4",
      "exampleSentence": "子供の頃の記憶を思い出しました。",
      "id": "7b7c82de-6acc-4165-9319-ebfc4aaea83e"
    }
  ],
  "quiz": [
    {
      "question": "ウィキニュースはいつ閉鎖することが決まりましたか。",
      "options": [
        "2004年",
        "2026年3月30日",
        "21年前",
        "最近"
      ],
      "correctIndex": 1,
      "explanation": "「2026年3月30日に、閉鎖することが決まりました。」",
      "id": "4aeb0ccd-3845-4fbb-921d-6e8b54594b32"
    }
  ],
  "tier": "n5n4",
  "sourceURL": "https://ja.wikinews.org/wiki/%E3%82%A6%E3%82%A3%E3%82%AD%E3%83%8B%E3%83%A5%E3%83%BC%E3%82%B9%E3%80%8121%E5%B9%B4%E3%81%AE%E6%AD%B4%E5%8F%B2%E3%81%AB%E5%B9%95%E3%82%92%E9%96%89%E3%81%98%E3%82%8B",
  "slug": "2026-05-06-21",
  "publishedAt": "2026-05-06T06:00:00+09:00"
}